{
  "event_id": "5fe3d431",
  "task_id": "ho_nav_recent_001",
  "step_index": 7,
  "pre_screenshot_path": "hybridstress_cockpit_full/transfer/screenshots/ho_nav_recent_001/pre_7.png",
  "post_screenshot_path": "hybridstress_cockpit_full/transfer/screenshots/ho_nav_recent_001/hybrid_run0_post_7.png",
  "action": "\u4ece\u6700\u8fd1\u76ee\u7684\u5730\u5217\u8868\u9009\u62e9'\u5bb6'\u5f00\u59cb\u5bfc\u822a",
  "postconditions": [
    {
      "subject": "destination",
      "relation": "contains",
      "object": "\u5bb6"
    },
    {
      "subject": "is_navigating",
      "relation": "value_is",
      "object": "true"
    }
  ],
  "emulator_snapshot_id": "transfer_ho_nav_recent_001_7",
  "label": "api_preferred",
  "fault_type": "state_rollback",
  "fault_severity": "mild",
  "timestamp_pre": 1775619210.725705,
  "timestamp_post": 1775619224.5267766,
  "hybrid_result": {
    "mode": "hybrid",
    "run_outcomes": [
      "failure",
      "failure",
      "failure"
    ],
    "majority_outcome": "failure",
    "run_durations_ms": [
      1081,
      1081,
      1080
    ]
  },
  "api_only_result": {
    "mode": "api_only",
    "run_outcomes": [
      "success",
      "success",
      "success"
    ],
    "majority_outcome": "success",
    "run_durations_ms": [
      582,
      581,
      582
    ]
  },
  "gui_only_result": {
    "mode": "gui_only",
    "run_outcomes": [
      "failure",
      "failure",
      "failure"
    ],
    "majority_outcome": "failure",
    "run_durations_ms": [
      2333,
      2332,
      2332
    ]
  }
}